{
  "institution_id": "G-SIFI-NORTH-01",
  "reporting_period": "2028-06-30T23:59:59Z",
  "posture_root": "0xMOCK_HASH_64_CHARS_LONG_FOR_TESTING_PURPOSES_ONLY",
  "g_sri_summary": {
    "score": 62.5,
    "status": "onTrack",
    "primary_risk_driver": "Cross-institution agent coupling"
  },
  "attestation_health": {
    "heartbeat_success_rate": 0.9998,
    "missing_window_count": 0,
    "pqc_integrity_status": true
  },
  "proof_bundles": [
    {
      "circuit_id": "GSM-TRANSITION-V1",
      "proof_hash": "0xMOCK_HASH_64_CHARS_LONG_FOR_TESTING_PURPOSES_ONLY",
      "verification_status": true
    },
    {
      "circuit_id": "FAIRNESS-CREDIT-V2",
      "proof_hash": "DUMMY_TOKEN_PLACEHOLDER_FOR_CI_COMPLIANCE",
      "verification_status": true
    }
  ],
  "signatures": [
    {
      "signer_role": "AI-Safety-Officer",
      "algorithm": "ML-DSA-65",
      "signature_hex": "mock_hash_64_chars_long_for_testing_purposes_onlymock_hash_64_chars_long_for_testing_purposes_only5cec981078"
    },
    {
      "signer_role": "Lead-Ethics-Auditor",
      "algorithm": "ML-DSA-65",
      "signature_hex": "mock_hash_64_chars_long_for_testing_purposes_onlymock_hash_64_chars_long_for_testing_purposes_onlyc9014"
    }
  ]
}
